MANIFEST.in
res_users_view.xml
setup.py
share_demo.xml
./__init__.py
./__openerp__.py
./ir_model.py
./res_users.py
./wizard/__init__.py
./wizard/share_wizard.py
i18n/ar.po
i18n/bg.po
i18n/bs.po
i18n/ca.po
i18n/cs.po
i18n/da.po
i18n/de.po
i18n/es.po
i18n/es_CR.po
i18n/es_MX.po
i18n/es_VE.po
i18n/et.po
i18n/fi.po
i18n/fr.po
i18n/gl.po
i18n/he.po
i18n/hr.po
i18n/hu.po
i18n/it.po
i18n/ja.po
i18n/lt.po
i18n/mk.po
i18n/mn.po
i18n/nl.po
i18n/pl.po
i18n/pt.po
i18n/pt_BR.po
i18n/ro.po
i18n/ru.po
i18n/share.pot
i18n/sl.po
i18n/sv.po
i18n/th.po
i18n/tr.po
i18n/zh_CN.po
images/share_wizard.jpeg
images/sharing_wizard_step1.jpeg
images/sharing_wizard_step2.jpeg
openerp_share.egg-info/PKG-INFO
openerp_share.egg-info/SOURCES.txt
openerp_share.egg-info/dependency_links.txt
openerp_share.egg-info/requires.txt
openerp_share.egg-info/top_level.txt
security/share_security.xml
static/src/img/share.png
static/src/js/share.js
static/src/xml/share.xml
wizard/share_wizard_view.xml